LICENSE.txt
MANIFEST.in
README
setup.cfg
setup.py
pyramid_mongodb/__init__.py
pyramid_mongodb.egg-info/PKG-INFO
pyramid_mongodb.egg-info/SOURCES.txt
pyramid_mongodb.egg-info/dependency_links.txt
pyramid_mongodb.egg-info/entry_points.txt
pyramid_mongodb.egg-info/not-zip-safe
pyramid_mongodb.egg-info/requires.txt
pyramid_mongodb.egg-info/top_level.txt
pyramid_mongodb/paster_templates/__init__.py
pyramid_mongodb/paster_templates/pyramid_mongodb/README.txt_tmpl
pyramid_mongodb/paster_templates/pyramid_mongodb/development.ini_tmpl
pyramid_mongodb/paster_templates/pyramid_mongodb/production.ini_tmpl
pyramid_mongodb/paster_templates/pyramid_mongodb/setup.cfg_tmpl
pyramid_mongodb/paster_templates/pyramid_mongodb/setup.py_tmpl
pyramid_mongodb/paster_templates/pyramid_mongodb/+package+/__init__.py_tmpl
pyramid_mongodb/paster_templates/pyramid_mongodb/+package+/resources.py
pyramid_mongodb/paster_templates/pyramid_mongodb/+package+/tests.py_tmpl
pyramid_mongodb/paster_templates/pyramid_mongodb/+package+/views.py_tmpl
pyramid_mongodb/paster_templates/pyramid_mongodb/+package+/static/favicon.ico
pyramid_mongodb/paster_templates/pyramid_mongodb/+package+/static/footerbg.png
pyramid_mongodb/paster_templates/pyramid_mongodb/+package+/static/headerbg.png
pyramid_mongodb/paster_templates/pyramid_mongodb/+package+/static/ie6.css
pyramid_mongodb/paster_templates/pyramid_mongodb/+package+/static/middlebg.png
pyramid_mongodb/paster_templates/pyramid_mongodb/+package+/static/pylons.css
pyramid_mongodb/paster_templates/pyramid_mongodb/+package+/static/pyramid-small.png
pyramid_mongodb/paster_templates/pyramid_mongodb/+package+/static/pyramid.png
pyramid_mongodb/paster_templates/pyramid_mongodb/+package+/static/transparent.gif
pyramid_mongodb/paster_templates/pyramid_mongodb/+package+/templates/mytemplate.pt_tmpl